skill_fleet/__init__.py
skill_fleet/_seed/skills/taxonomy_index.json
skill_fleet/_seed/skills/taxonomy_meta.json
skill_fleet/_seed/skills/_templates/skill_template.json
skill_fleet/agent/__init__.py
skill_fleet/agent/agent.py
skill_fleet/agent/modules.py
skill_fleet/agent/signatures.py
skill_fleet/agent/phase1/__init__.py
skill_fleet/agent/phase1/signatures.py
skill_fleet/agent/phase1/understand.py
skill_fleet/agent/phase2/__init__.py
skill_fleet/agent/phase2/scope.py
skill_fleet/agent/phase2/signatures.py
skill_fleet/analytics/__init__.py
skill_fleet/analytics/engine.py
skill_fleet/api/__init__.py
skill_fleet/api/app.py
skill_fleet/api/dependencies.py
skill_fleet/api/discovery.py
skill_fleet/api/jobs.py
skill_fleet/api/middleware/__init__.py
skill_fleet/api/routes/__init__.py
skill_fleet/api/routes/drafts.py
skill_fleet/api/routes/evaluation.py
skill_fleet/api/routes/hitl.py
skill_fleet/api/routes/jobs.py
skill_fleet/api/routes/optimization.py
skill_fleet/api/routes/skills.py
skill_fleet/api/routes/taxonomy.py
skill_fleet/api/routes/validation.py
skill_fleet/api/schemas/__init__.py
skill_fleet/api/schemas/hitl.py
skill_fleet/api/schemas/models.py
skill_fleet/cli/__init__.py
skill_fleet/cli/app.py
skill_fleet/cli/client.py
skill_fleet/cli/exceptions.py
skill_fleet/cli/interactive_cli.py
skill_fleet/cli/main.py
skill_fleet/cli/onboarding_cli.py
skill_fleet/cli/commands/__init__.py
skill_fleet/cli/commands/analytics.py
skill_fleet/cli/commands/chat.py
skill_fleet/cli/commands/create.py
skill_fleet/cli/commands/evaluate.py
skill_fleet/cli/commands/generate_xml.py
skill_fleet/cli/commands/list_skills.py
skill_fleet/cli/commands/migrate.py
skill_fleet/cli/commands/onboard.py
skill_fleet/cli/commands/optimize.py
skill_fleet/cli/commands/promote.py
skill_fleet/cli/commands/serve.py
skill_fleet/cli/commands/validate.py
skill_fleet/cli/hitl/__init__.py
skill_fleet/cli/hitl/runner.py
skill_fleet/cli/hitl/handlers/__init__.py
skill_fleet/cli/ui/__init__.py
skill_fleet-0.2.0.dist-info/METADATA
skill_fleet-0.2.0.dist-info/WHEEL
skill_fleet-0.2.0.dist-info/entry_points.txt
skill_fleet-0.2.0.dist-info/licenses/LICENSE
skill_fleet-0.2.0.dist-info/RECORD
