Metadata-Version: 2.4
Name: skill-fleet
Version: 0.2.0
Summary: Hierarchical skills taxonomy + DSPy workflow prototype
Project-URL: Homepage, https://github.com/Qredence/skill-fleet
Project-URL: Repository, https://github.com/Qredence/skill-fleet
Project-URL: Bug Tracker, https://github.com/Qredence/skill-fleet/issues
Project-URL: Documentation, https://github.com/Qredence/skill-fleet/tree/main/docs
Author: Qredence
License: Apache-2.0
License-File: LICENSE
Keywords: agents,cli,dspy,fastapi,skills,workflow
Classifier: Development Status :: 3 - Alpha
Classifier: Intended Audience :: Developers
Classifier: License :: OSI Approved :: Apache Software License
Classifier: Operating System :: OS Independent
Classifier: Programming Language :: Python :: 3
Classifier: Programming Language :: Python :: 3.12
Classifier: Topic :: Software Development :: Libraries :: Application Frameworks
Requires-Python: >=3.12
Requires-Dist: asyncpg>=0.31.0
Requires-Dist: click>=8.3.1
Requires-Dist: datasets>=4.4.2
Requires-Dist: dspy>=3.0.4
Requires-Dist: fastapi[standard]>=0.128.0
Requires-Dist: google-genai>=1.56.0
Requires-Dist: httpx>=0.28.1
Requires-Dist: litellm[proxy]>=1.80.16
Requires-Dist: mlflow>=3.8.1
Requires-Dist: openai>=2.14.0
Requires-Dist: prompt-toolkit>=3.0.52
Requires-Dist: pydantic>=2.12.5
Requires-Dist: python-dotenv>=1.2.1
Requires-Dist: pyyaml>=6.0.3
Requires-Dist: rich>=13.7.1
Requires-Dist: sqlalchemy>=2.0.45
Requires-Dist: tomli>=2.0
Requires-Dist: ty>=0.0.12
Requires-Dist: typer>=0.21.1
Requires-Dist: typing-extensions>=4.0
Requires-Dist: uvicorn[standard]>=0.31.1
Provides-Extra: dev
Requires-Dist: httpx>=0.28.1; extra == 'dev'
Requires-Dist: pytest-asyncio>=1.3.0; extra == 'dev'
Requires-Dist: pytest-cov>=7.0.0; extra == 'dev'
Requires-Dist: pytest>=8.0.0; extra == 'dev'
Requires-Dist: ruff>=0.8.0; extra == 'dev'
